<annotation>
	<folder>train</folder>
	<filename>hat_image104.JPG</filename>
	<path>/home/leeseoho/Tensorflow/od/images/train/hat_image104.JPG</path>
	<source>
		<database>Unknown</database>
	</source>
	<size>
		<width>676</width>
		<height>519</height>
		<depth>3</depth>
	</size>
	<segmented>0</segmented>
	<object>
		<name>hat</name>
		<pose>Unspecified</pose>
		<truncated>0</truncated>
		<difficult>0</difficult>
		<bndbox>
			<xmin>520</xmin>
			<ymin>179</ymin>
			<xmax>585</xmax>
			<ymax>212</ymax>
		</bndbox>
	</object>
</annotation>
